my_multiplypkg/__init__.py
my_multiplypkg/multiplication.py
my_multiplypkg-0.1.0.dist-info/METADATA
my_multiplypkg-0.1.0.dist-info/WHEEL
my_multiplypkg-0.1.0.dist-info/top_level.txt
my_multiplypkg-0.1.0.dist-info/RECORD
