Metadata-Version: 2.1
Name: my-multiplypkg
Version: 0.1.0
Summary: My first Python library for multiplication
Home-page: UNKNOWN
Author: Me
Author-email: UNKNOWN
License: MIT
Platform: UNKNOWN
